d4data/__init__.py
d4data/cli.py
d4data/core.py
d4data/prefect_tasks.py
d4data/datasets/__init__.py
d4data/datasets/csv_dataset.py
d4data/sources/__init__.py
d4data/sources/file.py
d4data/storage_clients/__init__.py
d4data/storage_clients/ftp.py
d4data/storage_clients/google.py
d4data/storage_clients/http.py
d4data-0.1.3.dist-info/AUTHORS.rst
d4data-0.1.3.dist-info/LICENSE
d4data-0.1.3.dist-info/METADATA
d4data-0.1.3.dist-info/WHEEL
d4data-0.1.3.dist-info/entry_points.txt
d4data-0.1.3.dist-info/top_level.txt
d4data-0.1.3.dist-info/RECORD
