Metadata-Version: 2.1
Name: d4data
Version: 0.1.3
Summary: Python Boilerplate contains all the boilerplate you need to create a Python package.
Home-page: https://github.com/kforti/d4data
Author: Kevin Fortier
Author-email: kevin.r.fortier@gmail.com
License: Apache Software License 2.0
Keywords: d4data
Platform: UNKNOWN
Classifier: Development Status :: 2 - Pre-Alpha
Classifier: Intended Audience :: Developers
Classifier: License :: OSI Approved :: Apache Software License
Classifier: Natural Language :: English
Classifier: Programming Language :: Python :: 3
Classifier: Programming Language :: Python :: 3.5
Classifier: Programming Language :: Python :: 3.6
Classifier: Programming Language :: Python :: 3.7
Classifier: Programming Language :: Python :: 3.8
Requires-Python: >=3.5
Requires-Dist: requests (==2.22.0)
Requires-Dist: torch
Requires-Dist: prefect
Requires-Dist: google-cloud-storage
